{
  "$schema": "https://developer.microsoft.com/json-schemas/fabric/item/report/definition/visualContainer/1.5.0/schema.json",
  "name": "59498afc9336e4151938",
  "position": {
    "x": 309.1741157349984,
    "y": 3.6953081561952033,
    "z": 2000,
    "height": 35,
    "width": 39,
    "tabOrder": 2000
  },
  "visual": {
    "visualType": "actionButton",
    "objects": {
      "icon": [
        {
          "properties": {
            "shapeType": {
              "expr": {
                "Literal": {
                  "Value": "'back'"
                }
              }
            },
            "lineColor": {
              "solid": {
                "color": {
                  "expr": {
                    "Literal": {
                      "Value": "'#FFC000'"
                    }
                  }
                }
              }
            },
            "lineWeight": {
              "expr": {
                "Literal": {
                  "Value": "2L"
                }
              }
            }
          },
          "selector": {
            "id": "default"
          }
        }
      ],
      "fill": [
        {
          "properties": {
            "show": {
              "expr": {
                "Literal": {
                  "Value": "false"
                }
              }
            }
          }
        },
        {
          "properties": {
            "image": {
              "image": {
                "name": {
                  "expr": {
                    "Literal": {
                      "Value": "'ICO_Clear_Filters_Gold.svg'"
                    }
                  }
                },
                "url": {
                  "expr": {
                    "ResourcePackageItem": {
                      "PackageName": "RegisteredResources",
                      "PackageType": 1,
                      "ItemName": "ICO_Clear_Filters_Gold5452931405679644.svg"
                    }
                  }
                },
                "scaling": {
                  "expr": {
                    "Literal": {
                      "Value": "'Normal'"
                    }
                  }
                }
              }
            },
            "fillColor": {
              "solid": {
                "color": {
                  "expr": {
                    "Measure": {
                      "Expression": {
                        "SourceRef": {
                          "Entity": "_All Measures"
                        }
                      },
                      "Property": "Transparent"
                    }
                  }
                }
              }
            },
            "transparency": {
              "expr": {
                "Literal": {
                  "Value": "0D"
                }
              }
            }
          },
          "selector": {
            "id": "default"
          }
        }
      ],
      "outline": [
        {
          "properties": {
            "show": {
              "expr": {
                "Literal": {
                  "Value": "false"
                }
              }
            }
          }
        }
      ]
    },
    "visualContainerObjects": {
      "visualLink": [
        {
          "properties": {
            "show": {
              "expr": {
                "Literal": {
                  "Value": "true"
                }
              }
            },
            "type": {
              "expr": {
                "Literal": {
                  "Value": "'Back'"
                }
              }
            },
            "bookmark": {
              "expr": {
                "Literal": {
                  "Value": "'925810855cfa580b6051'"
                }
              }
            },
            "tooltip": {
              "expr": {
                "Literal": {
                  "Value": "'Return to the Sales Analysis Page'"
                }
              }
            }
          }
        }
      ]
    },
    "drillFilterOtherVisuals": true
  },
  "parentGroupName": "bb308d646ac9e0d60386",
  "howCreated": "InsertVisualButton"
}